motus_command/__init__.py
motus_command/checkpoint.py
motus_command/cli.py
motus_command/codex_parser.py
motus_command/config.py
motus_command/conflict.py
motus_command/decisions.py
motus_command/drift_detector.py
motus_command/events.py
motus_command/exceptions.py
motus_command/gemini_parser.py
motus_command/harness.py
motus_command/hooks.py
motus_command/intent.py
motus_command/logging.py
motus_command/orchestrator.py
motus_command/process_detector.py
motus_command/protocols.py
motus_command/py.typed
motus_command/safety.py
motus_command/scope.py
motus_command/session_manager.py
motus_command/tracer.py
motus_command/transcript_parser.py
motus_command/builders/__init__.py
motus_command/builders/base.py
motus_command/builders/claude.py
motus_command/builders/codex.py
motus_command/builders/gemini.py
motus_command/commands/__init__.py
motus_command/commands/context_cmd.py
motus_command/commands/harness_cmd.py
motus_command/commands/history_cmd.py
motus_command/commands/hooks_cmd.py
motus_command/commands/list_cmd.py
motus_command/commands/models.py
motus_command/commands/prune_cmd.py
motus_command/commands/summary_cmd.py
motus_command/commands/utils.py
motus_command/ui/__init__.py
motus_command/ui/tui.py
motus_command/ui/tui_utils.py
motus_command/ui/web.py
motus_command/ui/static/dashboard.css
motus_command/ui/static/dashboard.js
motus_command/ui/templates/dashboard.html
motus_command-0.4.0.dist-info/METADATA
motus_command-0.4.0.dist-info/WHEEL
motus_command-0.4.0.dist-info/entry_points.txt
motus_command-0.4.0.dist-info/licenses/LICENSE
motus_command-0.4.0.dist-info/RECORD
