Metadata-Version: 2.4
Name: motus-command
Version: 0.4.0
Summary: Command Center for AI Agents - Real-time observability for Claude Code, Codex CLI, and AI coding assistants
Project-URL: Homepage, https://github.com/bnvoss/motus-command
Project-URL: Documentation, https://github.com/bnvoss/motus-command#readme
Project-URL: Repository, https://github.com/bnvoss/motus-command
Project-URL: Issues, https://github.com/bnvoss/motus-command/issues
Author-email: Ben Voss <ben@veritas.associates>
License-Expression: MIT
License-File: LICENSE
Keywords: agents,ai,claude,cli,codex,command-center,developer-tools,llm,monitoring,observability
Classifier: Development Status :: 4 - Beta
Classifier: Environment :: Console
Classifier: Intended Audience :: Developers
Classifier: License :: OSI Approved :: MIT License
Classifier: Operating System :: OS Independent
Classifier: Programming Language :: Python :: 3
Classifier: Programming Language :: Python :: 3.10
Classifier: Programming Language :: Python :: 3.11
Classifier: Programming Language :: Python :: 3.12
Classifier: Topic :: Software Development :: Libraries :: Python Modules
Classifier: Topic :: System :: Monitoring
Requires-Python: >=3.10
Requires-Dist: rich>=13.0.0
Requires-Dist: textual>=0.40.0
Provides-Extra: dev
Requires-Dist: beautifulsoup4>=4.12.0; extra == 'dev'
Requires-Dist: black>=23.0.0; extra == 'dev'
Requires-Dist: httpx>=0.25.0; extra == 'dev'
Requires-Dist: pre-commit>=3.0.0; extra == 'dev'
Requires-Dist: pytest-cov>=4.0.0; extra == 'dev'
Requires-Dist: pytest-textual-snapshot>=1.0.0; extra == 'dev'
Requires-Dist: pytest>=7.0.0; extra == 'dev'
Requires-Dist: ruff>=0.1.0; extra == 'dev'
Provides-Extra: web
Requires-Dist: fastapi>=0.100.0; extra == 'web'
Requires-Dist: uvicorn>=0.23.0; extra == 'web'
Requires-Dist: websockets>=11.0; extra == 'web'
